README.md
setup.py
datakund_cloud/GetAttributes.py
datakund_cloud/Progress.py
datakund_cloud/RunBot.py
datakund_cloud/__init__.py
datakund_cloud/datakund_cloud.py
datakund_cloud.egg-info/PKG-INFO
datakund_cloud.egg-info/SOURCES.txt
datakund_cloud.egg-info/dependency_links.txt
datakund_cloud.egg-info/requires.txt
datakund_cloud.egg-info/top_level.txt