Metadata-Version: 2.1
Name: datakund-cloud
Version: 1.0.4
Summary: Automation Library
Home-page: UNKNOWN
Author: DataKund
Author-email: datakund@gmail.com
License: Apache License 2.0
Platform: UNKNOWN
